{"train":[{"input":[[7,5,7,5,7,5,7],[7,5,7,5,7,5,7],[5,7,5,9,9,9,5],[5,7,5,9,9,9,5],[7,5,7,5,7,5,7],[7,5,7,5,7,5,7],[5,7,5,7,5,7,5],[5,7,5,7,5,7,5]],"output":[[7,5,7],[7,5,7]]},{"input":[[5,7,5,7],[5,7,5,7],[7,9,9,5],[7,9,9,5],[5,7,5,7],[5,7,5,7],[7,5,7,5],[7,5,7,5]],"output":[[5,7],[5,7]]},{"input":[[5,7,5,7,5],[5,7,5,7,5],[7,5,7,5,7],[7,5,7,5,7],[5,7,5,7,5],[9,9,5,7,5],[9,9,7,5,7],[7,5,7,5,7]],"output":[[5,7],[7,5]]}],"test":[{"input":[[5,7,5,7,5],[7,5,7,5,7],[7,9,9,9,9],[5,9,9,9,9],[5,7,5,7,5],[7,5,7,5,7],[7,5,7,5,7]],"output":[[5,7,5,7],[7,5,7,5]]}],"metadata":{"dataset_id":"solve_mask","transformation_id":"repair_rectangle_and_crop"}}